{
    "_id": "hero:corrin-novice-vacationer",
    "display": "Corrin: Novice Vacationer",
    "name": "Corrin",
    "color": "Blue",
    "weapon": [
        {
            "_id": "weapon:sealife-tome-plus",
            "unlock": 5
        },
        {
            "_id": "weapon:sealife-tome",
            "unlock": 3
        },
        {
            "_id": "weapon:elthunder",
            "unlock": 2
        },
        {
            "_id": "weapon:thunder",
            "unlock": 0
        }
    ],
    "special": [
        {
            "_id": "special:dragon-fang",
            "unlock": 4
        },
        {
            "_id": "special:dragon-gaze",
            "unlock": 3
        }
    ],
    "docType": "hero",
    "assist": [],
    "passiveA": [
        {
            "_id": "passive-a:swift-strike-2",
            "unlock": 5
        },
        {
            "_id": "passive-a:swift-strike-1",
            "unlock": 4
        },
        {
            "_id": "passive-a:darting-blow-1",
            "unlock": 3
        }
    ],
    "passiveC": [
        {
            "_id": "passive-c:fortify-fliers",
            "unlock": 4
        },
        {
            "_id": "passive-c:fortify-res-2",
            "unlock": 2
        },
        {
            "_id": "passive-c:fortify-res-1",
            "unlock": 1
        }
    ],
    "passiveB": [],
    "description": "A Hoshidan princess raised in Nohr. She won a ticket to a tropical island in a lottery. Appears in Fire Emblem Fates.",
    "weaponType": "Blue Tome",
    "moveType": "Flying",
    "origin": "Fire Emblem: Fates",
    "gender": "Female",
    "voiceActorEN": "Marcella Lentz-Pope",
    "voiceActorJP": "佐藤聡美",
    "releaseDate": "2017-07-28T00:00:00.000Z",
    "artistJP": "煎茶",
    "artistEN": "Sencha",
    "voiceActorJPEN": "Satou Satomi",
    "insights": [
        "Corrin is the only hero with Sealife Tome+.",
        "Corrin is the only hero with Sealife Tome.",
        "Corrin has the lowest <abbr title=\"Health Points\">HP</abbr> potential possible among Flying heroes."
    ],
    "refresher": false,
    "dragonflowers": 5,
    "epitet": "Novice Vacationer",
    "artist": "Sencha (煎茶)",
    "dialogue": [
        {
            "text": "Hello. I'm Corrin. I was resting on a beach when I heard someone calling my name. Was that you?",
            "context": "joined"
        },
        {
            "text": "Sharena and Anna complimented me on my swimsuit, but I have yet to see either of them wearing one.",
            "context": "castle"
        },
        {
            "text": "I won a ticket to an island resort but I wanted one of my siblings to use it. They all refused so I wound up going.",
            "context": "castle"
        },
        {
            "text": "Has my swimsuit caught your eye? If I could take you shopping, I'm sure we'd find one that suits you perfectly.",
            "context": "castle"
        },
        {
            "text": "I've never seen tropical fish before so I got this book that's all about them. Would you like to read it with me? Experiencing something for the first time is much better if I can share it with someone else!",
            "context": "castle"
        },
        {
            "text": "Do you know of any nearby Dragon Veins? If I find one, I can change some land into a beach for you.",
            "context": "castle"
        },
        {
            "text": "Sorry to show up in a swimsuit, but <Friend Name> gave me a message for you so I rushed out.",
            "context": "friend"
        },
        {
            "text": "What a lovely summer memory. I'll never forget it!",
            "context": "level"
        },
        {
            "text": "I'll do my best right up to the end of summer!",
            "context": "level"
        },
        {
            "text": "Perhaps my thoughts of the ocean distracted me...",
            "context": "level"
        },
        {
            "text": "Thank you! With this, I'll become stronger than the sun's own rays.",
            "context": "growth"
        },
        {
            "text": "The tropical island was amazing. I can see the crystal-clear water and blue sky every time I close my eyes. I spent so many years cooped up inside a fortress, so seeing such vivid colors was a whole new experience. I had always dreamed of such sights. I could have spent the rest of my life just staring out at the water... But I'm glad I didn't. I'm glad you called out to me, and I'm glad I answered. It allowed us to meet. Spending time here with you and making so many new friends are the perfect summer memories. This place is every bit as wonderful as that island. Oh, here I am just rambling on and on... Anyone ever tell you you're a pretty good listener? Well, I hope you'll tell me about yourself the next time we get a chance to talk.",
            "context": "maxed"
        }
    ],
    "tomeClass": 2,
    "regularHero": false,
    "permanentHero": false,
    "baseStats": {
        "hp": 16,
        "atk": 6,
        "spd": 7,
        "def": 4,
        "res": 6
    },
    "growthRates": {
        "hp": 40,
        "atk": 55,
        "spd": 60,
        "def": 40,
        "res": 45
    },
    "minStats": {
        "5": {
            "hp": {
                "base": 17,
                "low": 16,
                "high": 18
            },
            "atk": {
                "base": 7,
                "low": 6,
                "high": 8
            },
            "spd": {
                "base": 8,
                "low": 7,
                "high": 9
            },
            "def": {
                "base": 5,
                "low": 4,
                "high": 6
            },
            "res": {
                "base": 7,
                "low": 6,
                "high": 8
            },
            "rarity": 5
        }
    },
    "maxStats": {
        "5": {
            "hp": {
                "base": 34,
                "low": 31,
                "high": 37
            },
            "atk": {
                "base": 31,
                "low": 28,
                "high": 34
            },
            "spd": {
                "base": 34,
                "low": 31,
                "high": 37
            },
            "def": {
                "base": 22,
                "low": 19,
                "high": 25
            },
            "res": {
                "base": 26,
                "low": 23,
                "high": 30
            },
            "bst": {
                "low": null,
                "high": null,
                "base": 147
            }
        }
    }
}