{
    "refresher": false,
    "dragonflowers": 5,
    "docType": "hero",
    "name": "Marisa",
    "epitet": "Crimson Rabbit",
    "display": "Marisa: Crimson Rabbit",
    "description": "Skilled mercenary called the Crimson Flash. Received an order to participate in the Spring Festival as a bunny. Appears in Fire Emblem: The Sacred Stones.",
    "artist": "Tsukito (月戸)",
    "voiceActorEN": "Connor Kelley",
    "voiceActorJP": "中原麻衣",
    "dialogue": [
        {
            "text": "I am Marisa. Yes, that's right. I am a rabbit.",
            "context": "joined"
        },
        {
            "text": "I'm a rabbit. I survived the winter. Well, that's the idea.",
            "context": "castle"
        },
        {
            "text": "If Gerik and his band saw me like this... No, not thinking about that.",
            "context": "castle"
        },
        {
            "text": "Rabbits can sleep with their eyes open? To protect against attacks... I'll give it a try.",
            "context": "castle"
        },
        {
            "text": "Rabbits die if they get lonely? Er... Well...",
            "context": "castle"
        },
        {
            "text": "Rabbits wake up if they hear a tiny sound. I'm the same way.",
            "context": "castle"
        },
        {
            "text": "I'm Marisa. I'm here with a spring greeting from <Friend Name>.",
            "context": "friend"
        },
        {
            "text": "Strong, like a rabbit's kick.",
            "context": "level"
        },
        {
            "text": "Fast as a rabbit. I've been watching them.",
            "context": "level"
        },
        {
            "text": "Too slow to call myself a rabbit.",
            "context": "level"
        },
        {
            "text": "I want to hop.",
            "context": "growth"
        },
        {
            "text": "As a mercenary, I get jobs done. Whatever jobs come my way. That's how I live. If I'm told to cut down an enemy, I cut. If I'm told to protect someone, I protect them. To me, the contract is the law. Right now, my job is to be a rabbit. And so...I'm a rabbit. This is the first time I've had to dress up like this for a job... I don't really get it. But you seem to be having a good time, so that's good enough.",
            "context": "maxed"
        }
    ],
    "color": "Blue",
    "origin": "Fire Emblem: The Sacred Stones",
    "weapon": [
        {
            "_id": "weapon:flashing-carrot-plus",
            "unlock": 5
        },
        {
            "_id": "weapon:flashing-carrot",
            "unlock": 3
        },
        {
            "_id": "weapon:steel-lance",
            "unlock": 2
        },
        {
            "_id": "weapon:iron-lance",
            "unlock": 0
        }
    ],
    "assist": [
        {
            "_id": "assist:reposition",
            "unlock": 3
        }
    ],
    "weaponType": "Blue Lance",
    "tomeClass": 0,
    "moveType": "Flying",
    "regularHero": false,
    "permanentHero": false,
    "baseStats": {
        "hp": 17,
        "atk": 8,
        "spd": 7,
        "def": 5,
        "res": 5
    },
    "growthRates": {
        "hp": 55,
        "atk": 55,
        "spd": 70,
        "def": 50,
        "res": 35
    },
    "passiveB": [
        {
            "_id": "passive-b:spd-def-link-3",
            "unlock": 4
        },
        {
            "_id": "passive-b:spd-def-link-2",
            "unlock": 2
        },
        {
            "_id": "passive-b:spd-def-link-1",
            "unlock": 1
        }
    ],
    "passiveC": [
        {
            "_id": "passive-c:flier-guidance-3",
            "unlock": 5
        },
        {
            "_id": "passive-c:flier-guidance-2",
            "unlock": 4
        },
        {
            "_id": "passive-c:flier-guidance-1",
            "unlock": 3
        }
    ],
    "_id": "hero:marisa-crimson-rabbit",
    "minStats": {
        "5": {
            "hp": {
                "base": 18,
                "low": 17,
                "high": 19
            },
            "atk": {
                "base": 9,
                "low": 8,
                "high": 10
            },
            "spd": {
                "base": 8,
                "low": 7,
                "high": 9
            },
            "def": {
                "base": 6,
                "low": 5,
                "high": 7
            },
            "res": {
                "base": 6,
                "low": 5,
                "high": 7
            },
            "rarity": 5
        }
    },
    "maxStats": {
        "5": {
            "hp": {
                "base": 42,
                "low": 39,
                "high": 45
            },
            "atk": {
                "base": 33,
                "low": 30,
                "high": 36
            },
            "spd": {
                "base": 38,
                "low": 35,
                "high": 42
            },
            "def": {
                "base": 28,
                "low": 24,
                "high": 31
            },
            "res": {
                "base": 21,
                "low": 18,
                "high": 24
            },
            "bst": {
                "low": null,
                "high": null,
                "base": 162
            }
        }
    }
}