{
    "legendary": {
        "element": "Astra",
        "bst": 0,
        "stats": {
            "hp": 5,
            "def": 5
        },
        "duel": false,
        "duo_skill_id": null,
        "kind": 1,
        "pair_up": false
    },
    "refresher": false,
    "dragonflowers": 5,
    "docType": "hero",
    "name": "Naga",
    "epitet": "Dragon Divinity",
    "display": "Naga: Dragon Divinity",
    "description": "Ruler of the Divine Dragons. Takes on a variety of appearances in the presence of humans, and is said to have saved the world from despair. Appears in Fire Emblem: Mystery of the Emblem and Fire Emblem Awakening.",
    "artist": "Asatani Tomoyo (麻谷知世)",
    "voiceActorEN": "Mela Lee",
    "voiceActorJP": "佐藤聡美",
    "dialogue": [
        {
            "text": "I am she who is called Naga, the Divine Dragon. If you intend to face your fate, prove to me your resolve.",
            "context": "joined"
        },
        {
            "text": "I am but one of many divine dragons. We will continue to exist, in one form or another...",
            "context": "castle"
        },
        {
            "text": "As dragonkind approached extinction, we gave up our power for the sake of the future...and not simply our own.",
            "context": "castle"
        },
        {
            "text": "The world needs a guiding hand. My role is to steady that hand.",
            "context": "castle"
        },
        {
            "text": "Ritual cleansing is the best way to prepare your body for battle. Come now—I will show you how.",
            "context": "castle"
        },
        {
            "text": "I may not be human, but...the machinations of the children of men still draw my interest.",
            "context": "castle"
        },
        {
            "text": "The strength of your will is apparent. I see you are indeed worthy of calling <Friend Name> your friend.",
            "context": "friend"
        },
        {
            "text": "There exists no evil that the divine flame cannot purify...",
            "context": "level"
        },
        {
            "text": "I do not seek out violence, but... Let us say that even I cannot hold back the tide.",
            "context": "level"
        },
        {
            "text": "Do not trouble yourself with doubts. As I am now, I always have been.",
            "context": "level"
        },
        {
            "text": "Hm-hmm...very well, then. I shall see your desires are fulfilled.",
            "context": "growth"
        },
        {
            "text": "Come here. Gaze deep into my eyes, <Player Name>... Yes, I see. I, too, now understand the warmth and peace that arises when one is at your side. It is strange for one such as I, with strength rival to none, who watches over and guides the world... to drift into another world and find myself sharing feelings with mortals previously unknown to me. Yet...these feelings have put down roots in my heart. And your eyes tell me you feel the same warmth.",
            "context": "maxed"
        }
    ],
    "color": "Blue",
    "origin": "Fire Emblem: Awakening",
    "weapon": [
        {
            "_id": "weapon:divine-breath",
            "unlock": 5
        },
        {
            "_id": "weapon:flametongue",
            "unlock": 3
        },
        {
            "_id": "weapon:fire-breath-plus",
            "unlock": 2
        },
        {
            "_id": "weapon:fire-breath",
            "unlock": 0
        }
    ],
    "special": [
        {
            "_id": "special:luna",
            "unlock": 4
        },
        {
            "_id": "special:new-moon",
            "unlock": 3
        }
    ],
    "weaponType": "Blue Breath",
    "tomeClass": 0,
    "moveType": "Flying",
    "regularHero": false,
    "permanentHero": false,
    "baseStats": {
        "hp": 17,
        "atk": 5,
        "spd": 9,
        "def": 8,
        "res": 3
    },
    "growthRates": {
        "hp": 45,
        "atk": 55,
        "spd": 60,
        "def": 55,
        "res": 50
    },
    "passiveB": [
        {
            "_id": "passive-b:chill-spd-3",
            "unlock": 4
        },
        {
            "_id": "passive-b:chill-spd-2",
            "unlock": 2
        },
        {
            "_id": "passive-b:chill-spd-1",
            "unlock": 1
        }
    ],
    "passiveA": [
        {
            "_id": "passive-a:ar-o-atk-spd-3",
            "unlock": 5
        },
        {
            "_id": "passive-a:ar-o-atk-spd-2",
            "unlock": 4
        },
        {
            "_id": "passive-a:ar-o-atk-spd-1",
            "unlock": 3
        }
    ],
    "passiveC": [
        {
            "_id": "passive-c:divine-fang",
            "unlock": 5
        }
    ],
    "_id": "hero:naga-dragon-divinity",
    "minStats": {
        "5": {
            "hp": {
                "base": 18,
                "low": 17,
                "high": 19
            },
            "atk": {
                "base": 6,
                "low": 5,
                "high": 7
            },
            "spd": {
                "base": 10,
                "low": 9,
                "high": 11
            },
            "def": {
                "base": 9,
                "low": 8,
                "high": 10
            },
            "res": {
                "base": 4,
                "low": 3,
                "high": 5
            },
            "rarity": 5
        }
    },
    "maxStats": {
        "5": {
            "hp": {
                "base": 37,
                "low": 34,
                "high": 41
            },
            "atk": {
                "base": 30,
                "low": 27,
                "high": 33
            },
            "spd": {
                "base": 36,
                "low": 33,
                "high": 39
            },
            "def": {
                "base": 33,
                "low": 30,
                "high": 36
            },
            "res": {
                "base": 26,
                "low": 22,
                "high": 29
            },
            "bst": {
                "low": null,
                "high": null,
                "base": 162
            }
        }
    }
}